[
    {
      "id": 0,
      "title": "9 to 5",
      "type": "traditional",
      "filename": {
        "original": "/images/9-5.jpg"
      },
      "description": {
        "tools": "crayons and sketch paper",
        "more": "This drawing illustrates the monotony of a 9-5 job and how being aware of it can be mentally draining."
      }
    },
    {
        "id": 1,
        "title": "Sketch of Adam",
        "type": "traditional",
        "filename": {
          "original": "/images/adam.jpg"
        },
        "description": {
          "tools": "crayons and sketch paper",
          "more": "This is a quick sketch of my friend Adam after a night out."
        }
      },
      {
        "id": 2,
        "title": "Avocado",
        "type": "traditional",
        "filename": {
          "original": "/images/avocado.jpg"
        },
        "description": {
          "tools": "crayons and sketch paper",
          "more": "I wanted to draw parallels between a splitting headache and splitting open an avocado."
        }
      },
      {
        "id": 3,
        "title": "Bath",
        "type": "traditional",
        "filename": {
          "original": "/images/bath.jpg"
        },
        "description": {
          "tools": "crayons and sketch paper",
          "more": "I was testing out different crayons."
        }
      },
      {
        "id": 4,
        "title": "Bassist",
        "type": "traditional",
        "filename": {
          "original": "/images/bassist.jpg"
        },
        "description": {
          "tools": "crayons and sketch paper",
          "more": "This is a quick sketch of my friend testing out a rental bass."
        }
      },
      {
        "id": 5,
        "title": "Big Eye",
        "type": "traditional",
        "filename": {
          "original": "/images/big_eye.jpg"
        },
        "description": {
          "tools": "crayons and sketch paper",
          "more": "I was testing out blending with crayons."
        }
      },
      {
        "id": 6,
        "title": "Birth",
        "type": "traditional",
        "filename": {
          "original": "/images/birth.jpg"
        },
        "description": {
          "tools": "crayons and sketch paper",
          "more": "POV: you are being birthed."
        }
      },
      {
        "id": 7,
        "title": "Bleeding Out",
        "type": "traditional",
        "filename": {
          "original": "/images/bleeding_out.jpg"
        },
        "description": {
          "tools": "crayons and sketch paper",
          "more": "I wanted to illustrated extreme physical exhaustion."
        }
      },
      {
        "id": 8,
        "title": "Blindsided",
        "type": "traditional",
        "filename": {
          "original": "/images/blindsided.jpg"
        },
        "description": {
          "tools": "crayons and sketch paper",
          "more": "I wanted to illustrated the concept of one being blindsided by another person."
        }
      },
      {
        "id": 9,
        "title": "Blue Study",
        "type": "traditional",
        "filename": {
          "original": "/images/blue_study.jpg"
        },
        "description": {
          "tools": "crayons and sketch paper",
          "more": "This was my first attempt with colored crayons."
        }
      },
      {
        "id": 10,
        "title": "Card Design",
        "type": "traditional",
        "filename": {
          "original": "/images/card_design.jpg"
        },
        "description": {
          "tools": "crayons and sketch paper",
          "more": "This is a quick sketch of concept art for a card design."
        }
      },
      {
        "id": 11,
        "title": "Character Study",
        "type": "traditional",
        "filename": {
          "original": "/images/character_study.jpg"
        },
        "description": {
          "tools": "crayons and sketch paper",
          "more": "This is a quick sketch of concept art for a character design."
        }
      },
      {
        "id": 12,
        "title": "Hotline Miami Chicken Guy",
        "type": "traditional",
        "filename": {
          "original": "/images/chicken_guy.jpg"
        },
        "description": {
          "tools": "crayons and sketch paper",
          "more": "This is a quick sketch of fanart for the chicken guy in Hotline Miami."
        }
      },
      {
        "id": 13,
        "title": "Cloud Lady",
        "type": "traditional",
        "filename": {
          "original": "/images/cloud_lady.jpg"
        },
        "description": {
          "tools": "crayons and sketch paper",
          "more": "This is a quick sketch of the auto-generated key words: cloud, house, cape."
        }
      },
      {
        "id": 14,
        "title": "Color Study 1",
        "type": "traditional",
        "filename": {
          "original": "/images/color_study.jpg"
        },
        "description": {
          "tools": "crayons and sketch paper",
          "more": "I was testing out color crayons."
        }
      },
      {
        "id": 15,
        "title": "Color Study 2",
        "type": "traditional",
        "filename": {
          "original": "/images/color_study2.jpg"
        },
        "description": {
          "tools": "crayons and sketch paper",
          "more": "This is bad."
        }
      },
      {
        "id": 16,
        "title": "Sketch of my old coworker",
        "type": "traditional",
        "filename": {
          "original": "/images/coworker.jpg"
        },
        "description": {
          "tools": "crayons and sketch paper",
          "more": "I sketched my old coworker from Capco."
        }
      },
      {
        "id": 17,
        "title": "Desires",
        "type": "traditional",
        "filename": {
          "original": "/images/desires.jpg"
        },
        "description": {
          "tools": "crayons and sketch paper",
          "more": "I quickly sketched my short-term desires at the time."
        }
      },
      {
        "id": 18,
        "title": "Dog Won't Stop Moving",
        "type": "traditional",
        "filename": {
          "original": "/images/dog_wont_stop_moving.jpg"
        },
        "description": {
          "tools": "crayons and sketch paper",
          "more": "I was sketching at the park with my friend, and this owner's dog wouldn't sit still for my drawing."
        }
      },
      {
        "id": 19,
        "title": "Drowning",
        "type": "traditional",
        "filename": {
          "original": "/images/drowning.jpg"
        },
        "description": {
          "tools": "crayons and sketch paper",
          "more": "I wanted to illustrate being engulfed by relentless waves of emotion."
        }
      },
      {
        "id": 20,
        "title": "Faces",
        "type": "traditional",
        "filename": {
          "original": "/images/faces.jpg"
        },
        "description": {
          "tools": "crayons and sketch paper",
          "more": "This is a quick sketch after sharpening a brown crayon."
        }
      },
      {
        "id": 21,
        "title": "Firestone",
        "type": "traditional",
        "filename": {
          "original": "/images/firestone.jpg"
        },
        "description": {
          "tools": "crayons and sketch paper",
          "more": "I was using new crayons."
        }
      },
      {
        "id": 22,
        "title": "Frog Fighter Character",
        "type": "traditional",
        "filename": {
          "original": "/images/frog_fighter.jpg"
        },
        "description": {
          "tools": "crayons and sketch paper",
          "more": "This is a quick sketch of a frog character design."
        }
      },
      {
        "id": 23,
        "title": "Frog Warrior Character",
        "type": "traditional",
        "filename": {
          "original": "/images/frog_warrior.jpg"
        },
        "description": {
          "tools": "crayons and sketch paper",
          "more": "This is a quick sketch of a frog character design."
        }
      },
      {
        "id": 24,
        "title": "Two Girls Entering An Uber",
        "type": "traditional",
        "filename": {
          "original": "/images/girls_entering_uber.jpg"
        },
        "description": {
          "tools": "crayons and sketch paper",
          "more": "I decided to sketch people I saw on Queen Street West."
        }
      },
      {
        "id": 25,
        "title": "Gold Study",
        "type": "traditional",
        "filename": {
          "original": "/images/gold_study.jpg"
        },
        "description": {
          "tools": "crayons and sketch paper",
          "more": "This was a prompt for Inktober 2023."
        }
      },
      {
        "id": 26,
        "title": "Hand Practice",
        "type": "traditional",
        "filename": {
          "original": "/images/hand_practice.jpg"
        },
        "description": {
          "tools": "crayons and sketch paper",
          "more": "I wanted to do a study of hands and eyes."
        }
      },
      {
        "id": 27,
        "title": "Jeff Bezos",
        "type": "traditional",
        "filename": {
          "original": "/images/jeff_bezos.jpg"
        },
        "description": {
          "tools": "crayons and sketch paper",
          "more": "Jeff Bezos as Saitama."
        }
      },
      {
        "id": 28,
        "title": "Hug",
        "type": "traditional",
        "filename": {
          "original": "/images/hug.jpg"
        },
        "description": {
          "tools": "crayons and sketch paper",
          "more": "I wanted to illustrate the feeling of needing a hug."
        }
      },
      {
        "id": 29,
        "title": "Walls",
        "type": "traditional",
        "filename": {
          "original": "/images/incomplete_angel_wall.jpg"
        },
        "description": {
          "tools": "crayons and sketch paper",
          "more": "I wanted to draw the feeling of lowering one's walls."
        }
      },
      {
        "id": 30,
        "title": "Laundry Lady",
        "type": "traditional",
        "filename": {
          "original": "/images/laundry_lady.jpg"
        },
        "description": {
          "tools": "crayons and sketch paper",
          "more": "I drew this during a Drink&Draw session."
        }
      },
      {
        "id": 31,
        "title": "Light Purple",
        "type": "traditional",
        "filename": {
          "original": "/images/light_purple.jpg"
        },
        "description": {
          "tools": "crayons and sketch paper",
          "more": "This is a very simple sketch that I should really complete."
        }
      },
      {
        "id": 32,
        "title": "Lizard Angel",
        "type": "traditional",
        "filename": {
          "original": "/images/lizard_angel.jpg"
        },
        "description": {
          "tools": "crayons and sketch paper",
          "more": "I wanted to draw someone holding a skull."
        }
      },
      {
        "id": 33,
        "title": "Melting",
        "type": "traditional",
        "filename": {
          "original": "/images/melting.jpg"
        },
        "description": {
          "tools": "crayons and sketch paper",
          "more": "I wanted to draw extreme exhaustion."
        }
      },
      {
        "id": 34,
        "title": "Mermaid",
        "type": "traditional",
        "filename": {
          "original": "/images/mermaid.jpg"
        },
        "description": {
          "tools": "crayons and sketch paper",
          "more": "I like the way the scales turned out."
        }
      },
      {
        "id": 35,
        "title": "Merry Go Round",
        "type": "traditional",
        "filename": {
          "original": "/images/merry_go_round.jpg"
        },
        "description": {
          "tools": "crayons and sketch paper",
          "more": "I wanted to illustrate how I feel about routines."
        }
      },
      {
        "id": 36,
        "title": "Mouse Man",
        "type": "traditional",
        "filename": {
          "original": "/images/mouse_man.jpg"
        },
        "description": {
          "tools": "crayons and sketch paper",
          "more": "This is an interesting character design that I want to reuse."
        }
      },
      {
        "id": 37,
        "title": "Posture Study",
        "type": "traditional",
        "filename": {
          "original": "/images/posture_study.jpg"
        },
        "description": {
          "tools": "crayons and sketch paper",
          "more": "I wanted to practice anatomy."
        }
      },
      {
        "id": 38,
        "title": "Pot Study",
        "type": "traditional",
        "filename": {
          "original": "/images/pot_study.jpg"
        },
        "description": {
          "tools": "crayons and sketch paper",
          "more": "I saw plant pots and created these characters from them."
        }
      },
      {
        "id": 39,
        "title": "Colors Study",
        "type": "traditional",
        "filename": {
          "original": "/images/primary_colors_study.jpg"
        },
        "description": {
          "tools": "crayons and sketch paper",
          "more": "I wanted to use different shades of the colors I usually use."
        }
      },
      {
        "id": 40,
        "title": "Rei",
        "type": "traditional",
        "filename": {
          "original": "/images/rei.jpg"
        },
        "description": {
          "tools": "crayons and sketch paper",
          "more": "I drew Rei from Evangelion."
        }
      },
      {
        "id": 41,
        "title": "Dark Blue",
        "type": "traditional",
        "filename": {
          "original": "/images/sad_dark_blue.jpg"
        },
        "description": {
          "tools": "crayons and sketch paper",
          "more": "I wanted to illustrate substance abuse."
        }
      },
      {
        "id": 42,
        "title": "Sketchy",
        "type": "traditional",
        "filename": {
          "original": "/images/sketchy.jpg"
        },
        "description": {
          "tools": "crayons and sketch paper",
          "more": "I wanted to draw the feeling of brain fog."
        }
      },
      {
        "id": 43,
        "title": "Social Anxiety",
        "type": "traditional",
        "filename": {
          "original": "/images/social_anxiety.jpg"
        },
        "description": {
          "tools": "crayons and sketch paper",
          "more": "I wanted to draw what social anxiety can feel like."
        }
      },
      {
        "id": 44,
        "title": "Stoner Study",
        "type": "traditional",
        "filename": {
          "original": "/images/stoner_study.jpg"
        },
        "description": {
          "tools": "crayons and sketch paper",
          "more": "I drew this when I used to smoke a lot of weed."
        }
      },
      {
        "id": 45,
        "title": "Stoner",
        "type": "traditional",
        "filename": {
          "original": "/images/stoner.jpg"
        },
        "description": {
          "tools": "crayons and sketch paper",
          "more": "I wanted to draw when I was high."
        }
      },
      {
        "id": 46,
        "title": "Street Guy",
        "type": "traditional",
        "filename": {
          "original": "/images/street_guy.jpg"
        },
        "description": {
          "tools": "crayons and sketch paper",
          "more": "I drew a guy I saw on the street."
        }
      },
      {
        "id": 47,
        "title": "Tall Lady",
        "type": "traditional",
        "filename": {
          "original": "/images/tall_lady.jpg"
        },
        "description": {
          "tools": "crayons and sketch paper",
          "more": "This is an old character design."
        }
      },
      {
        "id": 48,
        "title": "Texture Study",
        "type": "traditional",
        "filename": {
          "original": "/images/texture_study.jpg"
        },
        "description": {
          "tools": "crayons and sketch paper",
          "more": "I was exploring drawing textures."
        }
      },
      {
        "id": 49,
        "title": "Three-Eyed Guy",
        "type": "traditional",
        "filename": {
          "original": "/images/three_eyed_guy.jpg"
        },
        "description": {
          "tools": "crayons and sketch paper",
          "more": "This is an illustratino of substance abusive."
        }
      },
      {
        "id": 50,
        "title": "Turquoise Snakes",
        "type": "traditional",
        "filename": {
          "original": "/images/turquoise_snakes.jpg"
        },
        "description": {
          "tools": "crayons and sketch paper",
          "more": "I wanted to draw demonic snakes."
        }
      },
      {
        "id": 51,
        "title": "Wizard",
        "type": "traditional",
        "filename": {
          "original": "/images/wizard.jpg"
        },
        "description": {
          "tools": "crayons and sketch paper",
          "more": "This is my friend's character for his book."
        }
      },
      {
        "id": 52,
        "title": "Yolanda",
        "type": "traditional",
        "filename": {
          "original": "/images/yolanda.jpg"
        },
        "description": {
          "tools": "crayons and sketch paper",
          "more": "This is a sketch of Yolanda."
        }
      },
      {
        "id": 53,
        "title": "Soup",
        "type": "animation",
        "filename": {
          "original": "/videos/soup.gif"
        },
        "description": {
          "tools": "Procreate",
          "more": "This is my first animation!"
        }
      },
      {
        "id": 54,
        "title": "Blue Fire",
        "type": "animation",
        "filename": {
          "original": "/videos/blue_fire.gif"
        },
        "description": {
          "tools": "Procreate",
          "more": "This is inspired by a tutorial online."
        }
      },
      {
        "id": 55,
        "title": "Plants And Flowers",
        "type": "animation",
        "filename": {
          "original": "/videos/plants.gif"
        },
        "description": {
          "tools": "Capcut and Flipbook",
          "more": "This is an attempt at stopmotion."
        }
      },
      {
        "id": 56,
        "title": "Biking",
        "type": "digital",
        "filename": {
          "original": "/images/biking_with_ex.png"
        },
        "description": {
          "tools": "Procreate",
          "more": "This is my second drawing on an iPad."
        }
      },
      {
        "id": 57,
        "title": "Working At A Coffeeshop",
        "type": "digital",
        "filename": {
          "original": "/images/coffee_shop_work.png"
        },
        "description": {
          "tools": "Procreate",
          "more": "I was testing out different fuchsia shades."
        }
      },
      {
        "id": 58,
        "title": "Facemasks",
        "type": "digital",
        "filename": {
          "original": "/images/facemasks_with_ex.png"
        },
        "description": {
          "tools": "Procreate",
          "more": "This is my first drawing on an iPad."
        }
      },
      {
        "id": 59,
        "title": "Ghost Design",
        "type": "digital",
        "filename": {
          "original": "/images/ghost_design.png"
        },
        "description": {
          "tools": "Procreate",
          "more": "I drew this during a trip to Montreal with friends."
        }
      },
      {
        "id": 60,
        "title": "Karaoke With Friends",
        "type": "digital",
        "filename": {
          "original": "/images/karaoke.png"
        },
        "description": {
          "tools": "Procreate",
          "more": "I had issues drawing the couch."
        }
      },
      {
        "id": 61,
        "title": "Moving Day",
        "type": "digital",
        "filename": {
          "original": "/images/moving.png"
        },
        "description": {
          "tools": "Procreate",
          "more": "I drew this a bit too quickly haha."
        }
      }
      
]